py_elasticinfra/__init__.py
py_elasticinfra/runner.py
py_elasticinfra/elk/__init__.py
py_elasticinfra/elk/elastic.py
py_elasticinfra/logger/__init__.py
py_elasticinfra/logger/logger.py
py_elasticinfra/logger/main.py
py_elasticinfra/metrics/__init__.py
py_elasticinfra/metrics/base.py
py_elasticinfra/metrics/cpu_load.py
py_elasticinfra/metrics/cpu_temp.py
py_elasticinfra/metrics/gpus.py
py_elasticinfra/metrics/memory.py
py_elasticinfra/utils/__init__.py
py_elasticinfra/utils/json.py
py_elasticinfra/utils/loop_thread.py
py_elasticinfra/utils/parse_config.py
py_metrics/__init__.py
py_metrics/runner.py
py_elasticinfrastructure-1.1.6.dist-info/LICENSE
py_elasticinfrastructure-1.1.6.dist-info/METADATA
py_elasticinfrastructure-1.1.6.dist-info/WHEEL
py_elasticinfrastructure-1.1.6.dist-info/top_level.txt
py_elasticinfrastructure-1.1.6.dist-info/RECORD
